torchkbnufft/__init__.py
torchkbnufft/_math.py
torchkbnufft/_version.py
torchkbnufft/_autograd/__init__.py
torchkbnufft/_autograd/interp.py
torchkbnufft/_nufft/__init__.py
torchkbnufft/_nufft/dcomp.py
torchkbnufft/_nufft/fft.py
torchkbnufft/_nufft/interp.py
torchkbnufft/_nufft/spmat.py
torchkbnufft/_nufft/toep.py
torchkbnufft/_nufft/utils.py
torchkbnufft/functional/__init__.py
torchkbnufft/functional/interp.py
torchkbnufft/functional/nufft.py
torchkbnufft/modules/__init__.py
torchkbnufft/modules/_kbmodule.py
torchkbnufft/modules/kbinterp.py
torchkbnufft/modules/kbnufft.py
torchkbnufft-1.5.2.dist-info/LICENSE
torchkbnufft-1.5.2.dist-info/METADATA
torchkbnufft-1.5.2.dist-info/WHEEL
torchkbnufft-1.5.2.dist-info/top_level.txt
torchkbnufft-1.5.2.dist-info/RECORD
