Metadata-Version: 2.1
Name: torchkbnufft
Version: 1.5.2
Summary: A high-level, easy-to-deploy non-uniform Fast Fourier Transform in PyTorch.
Author: torchkbnufft Authors
License: MIT
Project-URL: Homepage, https://torchkbnufft.readthedocs.io/en/stable/
Project-URL: Source, https://github.com/mmuckley/torchkbnufft
Classifier: Environment :: Console
Classifier: Natural Language :: English
Classifier: Programming Language :: Python :: 3
Classifier: Programming Language :: Python :: 3.8
Classifier: License :: OSI Approved :: MIT License
Classifier: Operating System :: OS Independent
Classifier: Development Status :: 4 - Beta
Classifier: Intended Audience :: Developers
Classifier: Topic :: Scientific/Engineering :: Artificial Intelligence
Classifier: Topic :: Scientific/Engineering :: Mathematics
Classifier: Topic :: Scientific/Engineering :: Medical Science Apps.
Classifier: Topic :: Scientific/Engineering :: Physics
Requires-Python: >=3.10
License-File: LICENSE
Requires-Dist: numpy>=2.0.0
Requires-Dist: scipy>=1.8.1
Requires-Dist: torch>=2.0
Provides-Extra: dev
Requires-Dist: black==24.10.0; extra == "dev"
Requires-Dist: flake8==6.1.0; extra == "dev"
Requires-Dist: mypy==1.13.0; extra == "dev"
Requires-Dist: pytest==8.3.3; extra == "dev"
Provides-Extra: tests
Requires-Dist: black==24.10.0; extra == "tests"
Requires-Dist: flake8==6.1.0; extra == "tests"
Requires-Dist: mypy==1.13.0; extra == "tests"
Requires-Dist: numpy==2.1.3; extra == "tests"
Requires-Dist: pytest==8.3.3; extra == "tests"
Requires-Dist: scipy==1.14.1; extra == "tests"
Requires-Dist: torch==2.5.1; extra == "tests"
Provides-Extra: docs
Requires-Dist: sphinx>=3.2.0; extra == "docs"
Requires-Dist: sphinx-rtd-theme>=0.5.1; extra == "docs"
Requires-Dist: sphinxcontrib-katex; extra == "docs"
Requires-Dist: sphinx-autodoc-typehints; extra == "docs"
